{
  "type": "panel",
  "items": {
    "login": {
      "type": "text",
      "label": {
        "en": "ConnectLife Cloud login (email)",
        "de": "ConnectLife-Cloud-Anmeldung (E-Mail)"
      },
      "newLine": true,
      "sm": 12,
      "md": 5,
      "lg": 4,
      "xl": 4,
      "style": {
        "maxWidth": "40ch"
      }
    },
    "password": {
      "type": "password",
      "label": {
        "en": "ConnectLife Cloud password",
        "de": "ConnectLife-Cloud-Passwort"
      },
      "newLine": true,
      "sm": 12,
      "md": 5,
      "lg": 4,
      "xl": 4,
      "style": {
        "maxWidth": "40ch"
      }
    },
    "pollInterval": {
      "type": "number",
      "label": {
        "en": "Polling interval in seconds",
        "de": "Abfrageintervall in Sekunden"
      },
      "min": 30,
      "max": 3600,
      "step": 10,
      "newLine": true,
      "sm": 12,
      "md": 4
    },
    "createRawStates": {
      "type": "checkbox",
      "label": {
        "en": "Create raw property states",
        "de": "Rohdatenpunkte anlegen"
      },
      "newLine": true
    },
    "allowRawWrites": {
      "type": "checkbox",
      "label": {
        "en": "Allow writes to unknown raw properties (advanced)",
        "de": "Schreiben auf unbekannte Rohdatenpunkte erlauben (erweitert)"
      },
      "newLine": true
    },
    "_footer": {
      "type": "staticText",
      "format": "html",
      "text": {
        "en": "When enabled, states below devices.&lt;device&gt;.raw can be written directly to the ConnectLife API. This is intended for testing functions that do not yet have a dedicated control state. Invalid values may be rejected by the device or cloud.<br>This adapter uses an unofficial, reverse-engineered cloud API. ConnectLife may change it without notice.<br>This adapter was developed with AI assistance and is available at <a href=\"https://github.com/Andiweli/ioBroker.connectlife\" target=\"_blank\" rel=\"noopener noreferrer\">https://github.com/Andiweli/ioBroker.connectlife</a><br>Based in part on <a href=\"https://github.com/Bilan/connectlife-api-connector\" target=\"_blank\" rel=\"noopener noreferrer\">https://github.com/Bilan/connectlife-api-connector</a>",
        "de": "Wenn aktiviert, können Datenpunkte unter devices.&lt;Gerät&gt;.raw direkt an die ConnectLife-API geschrieben werden. Das ist zum Testen von Funktionen gedacht, für die noch kein eigener Steuerdatenpunkt existiert. Ungültige Werte können vom Gerät oder von der Cloud abgelehnt werden.<br>Dieser Adapter verwendet eine inoffizielle, rekonstruierte Cloud-API. ConnectLife kann sie jederzeit ändern.<br>Dieser Adapter wurde KI-unterstützt entwickelt und ist erhältlich unter <a href=\"https://github.com/Andiweli/ioBroker.connectlife\" target=\"_blank\" rel=\"noopener noreferrer\">https://github.com/Andiweli/ioBroker.connectlife</a><br>Basiert auf Teilen von <a href=\"https://github.com/Bilan/connectlife-api-connector\" target=\"_blank\" rel=\"noopener noreferrer\">https://github.com/Bilan/connectlife-api-connector</a>"
      },
      "newLine": true,
      "sm": 12
    }
  }
}
